odoo/addons/web_searchbar_full_width/README.rst
odoo/addons/web_searchbar_full_width/__init__.py
odoo/addons/web_searchbar_full_width/__manifest__.py
odoo/addons/web_searchbar_full_width/i18n/ca.po
odoo/addons/web_searchbar_full_width/i18n/es.po
odoo/addons/web_searchbar_full_width/i18n/it.po
odoo/addons/web_searchbar_full_width/i18n/pt_BR.po
odoo/addons/web_searchbar_full_width/i18n/web_searchbar_full_width.pot
odoo/addons/web_searchbar_full_width/i18n/zh_CN.po
odoo/addons/web_searchbar_full_width/readme/CONTRIBUTORS.rst
odoo/addons/web_searchbar_full_width/readme/DESCRIPTION.rst
odoo/addons/web_searchbar_full_width/readme/USAGE.rst
odoo/addons/web_searchbar_full_width/static/description/icon.png
odoo/addons/web_searchbar_full_width/static/description/index.html
odoo/addons/web_searchbar_full_width/static/description/preview.png
odoo/addons/web_searchbar_full_width/static/src/scss/web_searchbar_full_width.scss
odoo_addon_web_searchbar_full_width-16.0.1.0.0.6.dist-info/METADATA
odoo_addon_web_searchbar_full_width-16.0.1.0.0.6.dist-info/WHEEL
odoo_addon_web_searchbar_full_width-16.0.1.0.0.6.dist-info/top_level.txt
odoo_addon_web_searchbar_full_width-16.0.1.0.0.6.dist-info/RECORD
